odoo/addons/account_banking_make_deposit/README.rst
odoo/addons/account_banking_make_deposit/__init__.py
odoo/addons/account_banking_make_deposit/__manifest__.py
odoo/addons/account_banking_make_deposit/data/deposit_method.xml
odoo/addons/account_banking_make_deposit/i18n/account_banking_make_deposit.pot
odoo/addons/account_banking_make_deposit/i18n/es.po
odoo/addons/account_banking_make_deposit/i18n/fr.po
odoo/addons/account_banking_make_deposit/i18n/pt.po
odoo/addons/account_banking_make_deposit/models/__init__.py
odoo/addons/account_banking_make_deposit/models/account_move_line.py
odoo/addons/account_banking_make_deposit/models/deposit_method.py
odoo/addons/account_banking_make_deposit/models/deposit_ticket.py
odoo/addons/account_banking_make_deposit/models/deposit_ticket_line.py
odoo/addons/account_banking_make_deposit/readme/CONFIGURATION.rst
odoo/addons/account_banking_make_deposit/readme/CONTRIBUTORS.rst
odoo/addons/account_banking_make_deposit/readme/DESCRIPTION.rst
odoo/addons/account_banking_make_deposit/readme/USAGE.rst
odoo/addons/account_banking_make_deposit/report/deposit_ticket.xml
odoo/addons/account_banking_make_deposit/report/deposit_ticket_report.xml
odoo/addons/account_banking_make_deposit/security/ir.model.access.csv
odoo/addons/account_banking_make_deposit/security/ir_rule.xml
odoo/addons/account_banking_make_deposit/security/res_groups.xml
odoo/addons/account_banking_make_deposit/static/description/icon.png
odoo/addons/account_banking_make_deposit/static/description/index.html
odoo/addons/account_banking_make_deposit/views/account_move_line.xml
odoo/addons/account_banking_make_deposit/views/deposit_method.xml
odoo/addons/account_banking_make_deposit/views/deposit_ticket.xml
odoo/addons/account_banking_make_deposit/wizard/__init__.py
odoo/addons/account_banking_make_deposit/wizard/add_deposit_items.py
odoo/addons/account_banking_make_deposit/wizard/add_deposit_items.xml
odoo12_addon_account_banking_make_deposit-12.0.1.0.0.99.dev17.dist-info/METADATA
odoo12_addon_account_banking_make_deposit-12.0.1.0.0.99.dev17.dist-info/WHEEL
odoo12_addon_account_banking_make_deposit-12.0.1.0.0.99.dev17.dist-info/top_level.txt
odoo12_addon_account_banking_make_deposit-12.0.1.0.0.99.dev17.dist-info/RECORD
